wz/__init__.py
wz-0.0.1.dist-info/LICENSE
wz-0.0.1.dist-info/METADATA
wz-0.0.1.dist-info/WHEEL
wz-0.0.1.dist-info/top_level.txt
wz-0.0.1.dist-info/RECORD
