Metadata-Version: 2.1
Name: wz
Version: 0.0.1
Summary: util
Home-page: https://zhenesis.com/
Author: Zhenxin (Jason) Wang
Author-email: wzhx.cc@gmail.com
License: UNKNOWN
Platform: UNKNOWN
Classifier: Programming Language :: Python :: 3
Classifier: License :: OSI Approved :: MIT License
Classifier: Operating System :: OS Independent
Requires-Python: >=3.6
